mediawiki_session/__init__.py
mediawiki_session/wsession.py
mediawiki_session-1.0.dist-info/licenses/LICENSE
mediawiki_session-1.0.dist-info/METADATA
mediawiki_session-1.0.dist-info/WHEEL
mediawiki_session-1.0.dist-info/top_level.txt
mediawiki_session-1.0.dist-info/RECORD
