Metadata-Version: 2.4
Name: mediawiki-session
Version: 1.0
Summary: TBD
Author: Gerard
Author-email: gweatherby@uchc.edu
License: MIT
Requires-Python: >=3.10
License-File: LICENSE
Requires-Dist: requests
Provides-Extra: yaml
Requires-Dist: pyyaml; extra == "yaml"
Dynamic: license-file
